{
  "collectionName": "components_content_lists",
  "info": {
    "name": "List",
    "icon": "clipboard-list",
    "description": ""
  },
  "options": {},
  "attributes": {
    "title": {
      "type": "string"
    },
    "className": {
      "type": "string"
    },
    "fullwidth": {
      "type": "boolean"
    },
    "columns": {
      "type": "enumeration",
      "enum": ["one", "two"]
    },
    "items": {
      "type": "component",
      "repeatable": true,
      "component": "content.list-item"
    }
  }
}
